codeyak/__init__.py
codeyak/__main__.py
codeyak/config.py
codeyak/py.typed
codeyak/apps/__init__.py
codeyak/apps/cli/__init__.py
codeyak/apps/cli/configure.py
codeyak/apps/cli/main.py
codeyak/domain/__init__.py
codeyak/domain/constants.py
codeyak/domain/exceptions.py
codeyak/domain/models.py
codeyak/infrastructure/__init__.py
codeyak/infrastructure/llm/azure.py
codeyak/infrastructure/vcs/diff_parser.py
codeyak/infrastructure/vcs/gitlab.py
codeyak/infrastructure/vcs/local_git.py
codeyak/prebuilt/__init__.py
codeyak/prebuilt/code-quality.yaml
codeyak/prebuilt/default.yaml
codeyak/prebuilt/security.yaml
codeyak/protocols/__init__.py
codeyak/services/__init__.py
codeyak/services/code.py
codeyak/services/context_builder.py
codeyak/services/reviewer.py
codeyak/services/summary.py
codeyak/services/context/__init__.py
codeyak/services/context/planner.py
codeyak/services/context/renderer.py
codeyak/services/context/skeleton.py
codeyak/services/context/symbol_index.py
codeyak/services/feedback/__init__.py
codeyak/services/feedback/console.py
codeyak/services/feedback/merge_request.py
codeyak/services/guidelines/__init__.py
codeyak/services/guidelines/generator.py
codeyak/services/guidelines/parser.py
codeyak/services/guidelines/provider.py
codeyak/ui/__init__.py
codeyak/ui/console.py
codeyak/ui/progress.py
codeyak-0.0.8.dist-info/METADATA
codeyak-0.0.8.dist-info/WHEEL
codeyak-0.0.8.dist-info/entry_points.txt
codeyak-0.0.8.dist-info/licenses/LICENSE
codeyak-0.0.8.dist-info/RECORD
