Metadata-Version: 2.4
Name: codeyak
Version: 0.0.8
Summary: A code review agent optimized for following strict guidelines
Project-URL: Homepage, https://github.com/ai-rayven/codeyak
Project-URL: Repository, https://github.com/ai-rayven/codeyak
Project-URL: Bug Tracker, https://github.com/ai-rayven/codeyak/issues
Author-email: Ray Martinez <raiselmartinez@gmail.com>
License-Expression: MIT
License-File: LICENSE
Keywords: ai,automation,azure-openai,code-review,gitlab,linting,llm
Classifier: Development Status :: 3 - Alpha
Classifier: Environment :: Console
Classifier: Intended Audience :: Developers
Classifier: License :: OSI Approved :: MIT License
Classifier: Operating System :: OS Independent
Classifier: Programming Language :: Python :: 3
Classifier: Programming Language :: Python :: 3.12
Classifier: Topic :: Software Development :: Quality Assurance
Classifier: Topic :: Software Development :: Testing
Requires-Python: >=3.12
Requires-Dist: click>=8.1.0
Requires-Dist: gitpython>=3.1.0
Requires-Dist: instructor>=1.14.1
Requires-Dist: langfuse>=3.11.2
Requires-Dist: openai>=2.15.0
Requires-Dist: pydantic-settings>=2.12.0
Requires-Dist: python-gitlab>=7.1.0
Requires-Dist: pyyaml>=6.0.1
Requires-Dist: rich>=14.0.0
Requires-Dist: tomli-w>=1.0.0
Requires-Dist: tree-sitter-c-sharp>=0.23.0
Requires-Dist: tree-sitter-javascript>=0.23.0
Requires-Dist: tree-sitter-python>=0.23.0
Requires-Dist: tree-sitter-typescript>=0.23.0
Requires-Dist: tree-sitter>=0.23.0
Provides-Extra: test
Requires-Dist: pytest-cov>=6.0.0; extra == 'test'
Requires-Dist: pytest-mock>=3.14.0; extra == 'test'
Requires-Dist: pytest>=8.0.0; extra == 'test'
